hdl/dut_sum.v
// ------------------------------------------------------------------
// DUT: Sum N 8-bit numbers
// ------------------------------------------------------------------
module dut_sum #(
    parameter N = 4
)(
    input  wire        clk,
    input  wire        rst,
    input  wire        en,
    input  wire [7:0]  data_in,
    output reg  [15:0] data_out,  // widen to 16 bits
    output reg         rdy
);

    // Internal registers
    reg [15:0] sum;      
    reg [2:0]  count;    
    reg         done;     

    // -----------------------------
    // Sequential logic
    // -----------------------------
    always @(posedge clk or posedge rst) begin
        if (rst) begin
            sum      <= 0;
            count    <= 0;
            data_out <= 0;
            rdy      <= 0;
            done     <= 0;
        end else begin
            rdy  <= done;  // output ready pulse
            done <= 0;     // reset done

            if (en) begin
                sum   <= sum + data_in;
                count <= count + 1;

                if (count == N-1) begin
                    data_out <= sum + data_in;  // final sum
                    done     <= 1;              // pulse rdy next cycle
                    sum      <= 0;              // reset sum
                    count    <= 0;              // reset count
                end
            end
        end
    end

    // -----------------------------
    // VCD waveform generation
    // -----------------------------
    initial begin
        $dumpfile("sim_build/wave.vcd");
        $dumpvars(0, dut_sum);
    end

endmodule

sim_build/wave.vcd
$date
	Sat Sep 20 21:49:14 2025
$end
$version
	Icarus Verilog
$end
$timescale
	1ps
$end
$scope module dut_sum $end
$var wire 1 ! clk $end
$var wire 8 " data_in [7:0] $end
$var wire 1 # en $end
$var wire 1 $ rst $end
$var reg 3 % count [2:0] $end
$var reg 16 & data_out [15:0] $end
$var reg 1 ' done $end
$var reg 1 ( rdy $end
$var reg 16 ) sum [15:0] $end
$upscope $end
$enddefinitions $end
#0
$dumpvars
b0 )
0(
0'
b0 &
b0 %
0$
0#
bz "
1!
$end
#5000
0!
#10000
1#
b101 "
1!
#15000
0!
#20000
b1010 "
b1 %
b101 )
1!
#25000
0!
#30000
b1111 "
b10 %
b1111 )
1!
#35000
0!
#40000
b10100 "
b11 %
b11110 )
1!
#45000
0!
#50000
0#
1'
b110010 &
b0 %
b0 )
1!
#55000
0!
#60000
0'
1(
1!
#65000
0!
#70000
0(
1!
#75000
0!
#80000
1#
b0 "
1!
#85000
0!
#90000
b1 %
1!
#95000
0!
#100000
b10 %
1!
#105000
0!
#110000
b11 %
1!
#115000
0!
#120000
0#
1'
b0 &
b0 %
1!
#125000
0!
#130000
0'
1(
1!
#135000
0!
#140000
0(
1!
#145000
0!
#150000
1#
b11111111 "
1!
#155000
0!
#160000
b1 "
b1 %
b11111111 )
1!
#165000
0!
#170000
b0 "
b10 %
b100000000 )
1!
#175000
0!
#180000
b11 %
1!
#185000
0!
#190000
0#
b0 )
1'
b100000000 &
b0 %
1!
#195000
0!
#200000
0'
1(
1!
#205000
0!
#210000
0(
1!
#215000
0!
#220000
1#
b1 "
1!
#225000
0!
#230000
b10 "
b1 %
b1 )
1!
#235000
0!
#240000
b11 "
b10 %
b11 )
1!
#245000
0!
#250000
b100 "
b11 %
b110 )
1!
#255000
0!
#260000
0#
1'
b1010 &
b0 %
b0 )
1!
#265000
0!
#270000
0'
1(
1!
#275000
0!
#280000
0(
1!
